mh1_copilot/__init__.py
mh1_copilot/cli.py
mh1_copilot-0.6.0.dist-info/METADATA
mh1_copilot-0.6.0.dist-info/WHEEL
mh1_copilot-0.6.0.dist-info/entry_points.txt
mh1_copilot-0.6.0.dist-info/top_level.txt
mh1_copilot-0.6.0.dist-info/RECORD
