Metadata-Version: 2.4
Name: mh1-copilot
Version: 0.6.0
Summary: AI-Powered Marketing Operations Copilot
Author-email: MarketerHire <engineering@marketerhire.com>
License: MIT
Project-URL: Homepage, https://github.com/NewGameJay/mh1
Project-URL: Repository, https://github.com/NewGameJay/mh1
Project-URL: Documentation, https://github.com/NewGameJay/mh1#readme
Project-URL: Bug Tracker, https://github.com/NewGameJay/mh1/issues
Keywords: marketing,automation,ai,copilot,hubspot,crm,anthropic,claude
Classifier: Development Status :: 4 - Beta
Classifier: Environment :: Console
Classifier: Intended Audience :: Developers
Classifier: Intended Audience :: End Users/Desktop
Classifier: License :: OSI Approved :: MIT License
Classifier: Operating System :: OS Independent
Classifier: Programming Language :: Python :: 3
Classifier: Programming Language :: Python :: 3.10
Classifier: Programming Language :: Python :: 3.11
Classifier: Programming Language :: Python :: 3.12
Classifier: Topic :: Office/Business
Requires-Python: >=3.10
Provides-Extra: full
Requires-Dist: firebase-admin>=6.0; extra == "full"
Requires-Dist: praw>=7.7.0; extra == "full"
Requires-Dist: tweepy>=4.14.0; extra == "full"
Requires-Dist: anthropic>=0.18.0; extra == "full"
Provides-Extra: dev
Requires-Dist: pytest>=7.0; extra == "dev"
Requires-Dist: pytest-cov>=4.0; extra == "dev"
Requires-Dist: black>=23.0; extra == "dev"
Requires-Dist: ruff>=0.1.0; extra == "dev"
Provides-Extra: api
Requires-Dist: anthropic>=0.18.0; extra == "api"
